{
  "CODIGO": "85299040",
  "EXCECAO_FISCAL": null,
  "DESCRICAO": "Maquinas aparelhos e materiais eletricos e suas partes aparelhos de gravacao ou de reproducao de som aparelhos de gravacao ou de reproducao de imagens e de som em televisao e suas partes e acessorios Partes reconheciveis como exclusiva ou principalmente destinadas aos aparelhos das posicoes 85 25 a 85 28 De aparelhos da subposicao 8526 91",
  "ALIQ_FED_NAC": 19.55,
  "ALIQ_FED_IMP": 21.55,
  "ALIQ_ESTADUAL": 18.00,
  "ALIQ_MUNICIPAL": 0.00,
  "DT_INICIO_VIG": "2025-10-20",
  "DT_FIM_VIG": "2025-11-30",
  "FONTE": "IBPT/empresometro.com.br"
}