[
  {
    "CODIGO": "40121900",
    "EXCECAO_FISCAL": null,
    "DESCRICAO": "Outspneumaticos recauchutados,de borracha",
    "ALIQ_FED_NAC": 13.45,
    "ALIQ_FED_IMP": 19.29,
    "ALIQ_ESTADUAL": 20.50,
    "ALIQ_MUNICIPAL": 0.00,
    "DT_INICIO_VIG": "2025-10-20",
    "DT_FIM_VIG": "2025-11-30",
    "FONTE": "IBPT/empresometro.com.br"
  },
  {
    "CODIGO": "40121900",
    "EXCECAO_FISCAL": "01",
    "DESCRICAO": "Remoldados, exceto para maquinas e tratores agricolas",
    "ALIQ_FED_NAC": 16.16,
    "ALIQ_FED_IMP": 22.00,
    "ALIQ_ESTADUAL": 20.50,
    "ALIQ_MUNICIPAL": 0.00,
    "DT_INICIO_VIG": "2025-10-20",
    "DT_FIM_VIG": "2025-11-30",
    "FONTE": "IBPT/empresometro.com.br"
  },
  {
    "CODIGO": "40121900",
    "EXCECAO_FISCAL": "02",
    "DESCRICAO": "Remoldados, para maquinas e tratores agricolas",
    "ALIQ_FED_NAC": 13.84,
    "ALIQ_FED_IMP": 19.68,
    "ALIQ_ESTADUAL": 20.50,
    "ALIQ_MUNICIPAL": 0.00,
    "DT_INICIO_VIG": "2025-10-20",
    "DT_FIM_VIG": "2025-11-30",
    "FONTE": "IBPT/empresometro.com.br"
  }
]