[
  {
    "CODIGO": "70134900",
    "EXCECAO_FISCAL": null,
    "DESCRICAO": "Outros objs.de vidro,p/serv.mesa/cozinha",
    "ALIQ_FED_NAC": 17.45,
    "ALIQ_FED_IMP": 32.55,
    "ALIQ_ESTADUAL": 28.00,
    "ALIQ_MUNICIPAL": 0.00,
    "DT_INICIO_VIG": "2025-11-20",
    "DT_FIM_VIG": "2026-01-31",
    "FONTE": "IBPT/empresometro.com.br"
  },
  {
    "CODIGO": "70134900",
    "EXCECAO_FISCAL": "01",
    "DESCRICAO": "Decantadores de vinho",
    "ALIQ_FED_NAC": 19.27,
    "ALIQ_FED_IMP": 34.37,
    "ALIQ_ESTADUAL": 28.00,
    "ALIQ_MUNICIPAL": 0.00,
    "DT_INICIO_VIG": "2025-11-20",
    "DT_FIM_VIG": "2026-01-31",
    "FONTE": "IBPT/empresometro.com.br"
  }
]