[
  {
    "CODIGO": "70052100",
    "EXCECAO_FISCAL": null,
    "DESCRICAO": "Vidro e suas obras Vidro flotado e vidro desbastado ou polido numa ou em ambas as faces em chapas ou em folhas mesmo com camada absorvente refletora ou nao mas nao trabalhado de outro modo corado na massa opacificado folheado chapeado ou simplesmente desbastado",
    "ALIQ_FED_NAC": 15.17,
    "ALIQ_FED_IMP": 19.50,
    "ALIQ_ESTADUAL": 12.00,
    "ALIQ_MUNICIPAL": 0.00,
    "DT_INICIO_VIG": "2025-11-20",
    "DT_FIM_VIG": "2026-01-31",
    "FONTE": "IBPT/empresometro.com.br"
  },
  {
    "CODIGO": "70052100",
    "EXCECAO_FISCAL": "01",
    "DESCRICAO": "De vidro optico",
    "ALIQ_FED_NAC": 13.45,
    "ALIQ_FED_IMP": 17.78,
    "ALIQ_ESTADUAL": 12.00,
    "ALIQ_MUNICIPAL": 0.00,
    "DT_INICIO_VIG": "2025-11-20",
    "DT_FIM_VIG": "2026-01-31",
    "FONTE": "IBPT/empresometro.com.br"
  }
]